{"profile":{"cite":{"home":{"artist":"Takehiro Tobinaga","preposition":"by","icon":"adobe-icon-behance","title":"Kumano Kodo","url":"https://www.behance.net/gallery/28102497/Adobe-New-Creative-Cloud-2015?promoid=KSDQA","target":"_self","position":"bottom-left"}},"manage":{"deprovisionedTitle":"Ready to buy?","plans":"Choose a plan","plansLink":"https://creative.adobe.com/plans","account":"Manage account","accountLink":"https://accounts.adobe.com/?promoid=KRUVI","team":"Manage team","teamLink":"https://creative.adobe.com/team/admin?promoid=KRUVJ","enterprise":"Manage enterprise","enterpriseLink":"https://aedash.adobe.com?promoid=KRUVK"},"apps":{"appsTitle":"CREATIVE CLOUD APPS","desktop":"Desktop","desktopLink":"/creativecloud/catalog/desktop.html?promoid=KRUVM","addons":"Add-ons","addonsLink":"https://creative.adobe.com/addons?promoid=KRUVN","mobile":"Mobile","mobileLink":"/creativecloud/catalog/mobile.html?promoid=KRUVO"},"assets":{"assetsTitle":"ASSETS","files":"Files","filesCC":"Creative Cloud Files","filesLink":"https://assets.adobe.com/files?promoid=KRUVP","dc":"Document Cloud Files","dcLink":"https://cloud.acrobat.com/folder?promoid=KSBOT","photos":"Photos","photosLink":"https://lightroom.adobe.com?promoid=KRUVQ","fonts":"Fonts","fontsLink":"https://typekit.com/fonts?ref=globalnav&promoid=KRUVR","colors":"Colors","colorsLink":"https://kuler.adobe.com?promoid=KRUVS","libraries":"Libraries","librariesLink":"https://assets.adobe.com/assets/libraries?promoid=KRUVT"},"community":{"communityTitle":"COMMUNITY","network":"Creative Network","networkLink":"https://www.behance.net?sso_inbound=1&promoid=KRUVU","portfolio":"Portfolio Website","portfolioLink":"https://www.behance.net/prosite?sso_inbound=1&promoid=KRUVV"},"dc":{"dcTitle":"DOCUMENT CLOUD APPS","desktop":"Desktop","desktopLink":"https://cloud.acrobat.com/acrobat?promoid=KSBOQ","mobile":"Mobile","mobileLink":"https://documents.adobe.com?promoid=KSBOR","web":"Web","webLink":"https://documents.adobe.com?promoid=KSBOS"},"stock":{"stockTitle":"ADOBE STOCK","stock":"Photos, Illustrations & Vectors","stockLink":"https://stock.adobe.com/?sso_inbound=1&locale=en_US&promoid=KSSOX"},"signOut":"Sign out"},"campaigns":{"article":{"inverseColoring":"false","text":"<h1>Your creative world.<br>\nPerfectly in sync.<\/h1>\n<p>The latest release of Creative Cloud brings together everything you need to create whatever you want, wherever you are. Great new mobile apps. Your favorite desktop tools. Every asset at your fingertips, including Adobe Stock. And it's all connected and up to date with the power of CreativeSync.<\/p>\n","list":[{"cssClass":"cta","link":"http://www.adobe.com/creativecloud/features.html?promoid=KSDPX","themeId":"","linkIcon":"","text":"See what's new in Creative Cloud","type":"link","target":"","position":"bottom-left"},{"cssClass":"","link":"/creativecloud.html?promoid=KSDPY","themeId":"","linkIcon":"","text":"Learn about Creative Cloud","type":"button","target":"","position":"bottom-left"}]},"background":{"position":"50% 50%","selector":"main.lobby figure:nth-of-type(1):before","url":"http://wwwimages.adobe.com/content/dam/acom/en/lobby/lobby-bg-max-takehiro-loggedin-1400x860.jpg"}}}