{"profile":{"cite":{"home":{"artist":"Maria Gronlund","preposition":"by","icon":"adobe-icon-behance","title":"Cosmos","url":"https://www.behance.net/gallery/21107983/Cosmos?promoid=KSDQA","target":"_self","position":"bottom-left"}},"manage":{"deprovisionedTitle":"Ready to buy?","plans":"Choose a plan","plansLink":"https://creative.adobe.com/plans","account":"Manage account","accountLink":"https://accounts.adobe.com/?promoid=KRUVI","team":"Manage team","teamLink":"https://creative.adobe.com/team/admin?promoid=KRUVJ","enterprise":"Manage enterprise","enterpriseLink":"https://aedash.adobe.com?promoid=KRUVK"},"apps":{"appsTitle":"CREATIVE CLOUD APPS","desktop":"Desktop","desktopLink":"/creativecloud/catalog/desktop.html?promoid=KRUVM","addons":"Add-ons","addonsLink":"https://creative.adobe.com/addons?promoid=KRUVN","mobile":"Mobile","mobileLink":"/creativecloud/catalog/mobile.html?promoid=KRUVO"},"assets":{"assetsTitle":"ASSETS","files":"Files","filesCC":"Creative Cloud Files","filesLink":"https://assets.adobe.com/files?promoid=KRUVP","dc":"Document Cloud Files","dcLink":"https://cloud.acrobat.com/folder?promoid=KSBOT","photos":"Photos","photosLink":"https://lightroom.adobe.com?promoid=KRUVQ","fonts":"Fonts","fontsLink":"https://typekit.com/fonts?ref=globalnav&promoid=KRUVR","colors":"Colors","colorsLink":"https://kuler.adobe.com?promoid=KRUVS","libraries":"Libraries","librariesLink":"https://assets.adobe.com/assets/libraries?promoid=KRUVT"},"community":{"communityTitle":"COMMUNITY","network":"Creative Network","networkLink":"https://www.behance.net?sso_inbound=1&promoid=KRUVU","portfolio":"Portfolio Website","portfolioLink":"https://www.behance.net/prosite?sso_inbound=1&promoid=KRUVV"},"dc":{"dcTitle":"DOCUMENT CLOUD APPS","desktop":"Desktop","desktopLink":"https://cloud.acrobat.com/acrobat?promoid=KSBOQ","mobile":"Mobile","mobileLink":"https://documents.adobe.com?promoid=KSBOR","web":"Web","webLink":"https://documents.adobe.com?promoid=KSBOS"},"stock":{"stockTitle":"ADOBE STOCK","stock":"Photos, Illustrations & Vectors","stockLink":"https://stock.adobe.com/?sso_inbound=1&locale=en_US&promoid=KSSOX"},"signOut":"Sign out"},"campaigns":{"article":{"inverseColoring":"true","text":"<h1>Ten things you\u2019ll love about Adobe Stock.<\/h1>\n<p>Your first 10 images are free for a limited time. Get access to more than 40 million high-quality royalty-free images, graphics and videos right inside your apps.<\/p>\n","list":[{"cssClass":"","link":"https://stock.adobe.com/","themeId":"","linkIcon":"","text":"Get your free images","type":"button","target":"","position":"bottom-left"}]},"background":{"selector":"main.lobby figure:nth-of-type(1):before","url":"http://wwwimages.adobe.com/content/dam/acom/en/lobby/lobby-bg-bf2015-loggedin-1400x860.jpg","mobileUrl":null,"position":"70% 44%","mobilePosition":"50% 50%"}}}