{"results":{"current":[{"location":"UNCX","phrase":"CLOUDY","description":"Cloudy","temp":75,"temp_unit":"F","aptemp":74,"aptemp_unit":"F","wndchl":75,"wndchl_unit":"F","rhumid":33,"wind_dir":"SW","windspeed":5,"windspeed_unit":"mph","pressure":"29.970","pressure_unit":"in\/Hg","visibility":10,"visibility_unit":"mi","icon":"07","image":"http:\/\/graphics8.nytimes.com\/images\/apps\/weather\/7.gif","updated":"2016-03-10 13:25:08","city":"New York","state":"NY","country":"United States","zipcode":"10001","date":"2016-03-10T00:00:00-05:00"}],"seven_day_forecast":[{"location":"UNCX","day":"Thursday","icon":"04","image":"http:\/\/graphics8.nytimes.com\/images\/apps\/weather\/4.gif","high":79,"high_unit":"F","low":57,"low_unit":"F","phrase":"Very warm with times of clouds and sun","updated":"2016-03-10 13:29:30","city":"New York","state":"NY","country":"United States","zipcode":"10001","date":"2016-03-10T00:00:00-05:00"},{"location":"UNCX","day":"Friday","icon":"02","image":"http:\/\/graphics8.nytimes.com\/images\/apps\/weather\/2.gif","high":63,"high_unit":"F","low":41,"low_unit":"F","phrase":"Sunshine; breezy, pleasant and cooler","updated":"2016-03-10 13:29:30","city":"New York","state":"NY","country":"United States","zipcode":"10001","date":"2016-03-11T00:00:00-05:00"},{"location":"UNCX","day":"Saturday","icon":"04","image":"http:\/\/graphics8.nytimes.com\/images\/apps\/weather\/4.gif","high":63,"high_unit":"F","low":51,"low_unit":"F","phrase":"Intervals of clouds and sunshine","updated":"2016-03-10 13:29:30","city":"New York","state":"NY","country":"United States","zipcode":"10001","date":"2016-03-12T00:00:00-05:00"},{"location":"UNCX","day":"Sunday","icon":"06","image":"http:\/\/graphics8.nytimes.com\/images\/apps\/weather\/6.gif","high":63,"high_unit":"F","low":48,"low_unit":"F","phrase":"Mostly cloudy and mild","updated":"2016-03-10 13:29:30","city":"New York","state":"NY","country":"United States","zipcode":"10001","date":"2016-03-13T00:00:00-05:00"},{"location":"UNCX","day":"Monday","icon":"12","image":"http:\/\/graphics8.nytimes.com\/images\/apps\/weather\/12.gif","high":55,"high_unit":"F","low":47,"low_unit":"F","phrase":"Mostly cloudy, rain ending; cooler","updated":"2016-03-10 13:29:30","city":"New York","state":"NY","country":"United States","zipcode":"10001","date":"2016-03-14T00:00:00-04:00"},{"location":"UNCX","day":"Tuesday","icon":"06","image":"http:\/\/graphics8.nytimes.com\/images\/apps\/weather\/6.gif","high":61,"high_unit":"F","low":52,"low_unit":"F","phrase":"Chance for a couple of showers","updated":"2016-03-10 13:29:30","city":"New York","state":"NY","country":"United States","zipcode":"10001","date":"2016-03-15T00:00:00-04:00"},{"location":"UNCX","day":"Wednesday","icon":"02","image":"http:\/\/graphics8.nytimes.com\/images\/apps\/weather\/2.gif","high":59,"high_unit":"F","low":49,"low_unit":"F","phrase":"Sunshine and patchy clouds","updated":"2016-03-10 13:29:30","city":"New York","state":"NY","country":"United States","zipcode":"10001","date":"2016-03-16T00:00:00-04:00"}],"is_default":false}}